__init__.py
apuf.py
challenges.py
apuf-0.2.0.dist-info/licenses/LICENSE
apuf-0.2.0.dist-info/METADATA
apuf-0.2.0.dist-info/WHEEL
apuf-0.2.0.dist-info/top_level.txt
apuf-0.2.0.dist-info/RECORD
