Metadata-Version: 2.4
Name: apuf
Version: 0.2.0
Summary: A library for simulating Arbiter PUFs and other delay-based PUFs.
Author-email: Nikita Tripathi <ntripathi99@gmail.com>
License-Expression: MIT
Project-URL: Homepage, https://github.com/nikita-tripathi-geo/APUF-simulation
Project-URL: Issues, https://github.com/nikita-tripathi-geo/APUF-simulation/issues
Classifier: Programming Language :: Python :: 3
Classifier: Operating System :: OS Independent
Classifier: Development Status :: 4 - Beta
Classifier: Intended Audience :: Education
Classifier: Intended Audience :: Information Technology
Classifier: Intended Audience :: Science/Research
Classifier: Natural Language :: English
Classifier: Topic :: Security
Requires-Python: >=3.9
License-File: LICENSE
Dynamic: license-file
